{"cameraMode":{"drawMode":0,"name":"Shaded","section":"Shading Mode"},"sceneLighting":true,"audioPlay":false,"sceneViewState":{"showFog":true,"showMaterialUpdate":false,"showSkybox":true,"showFlares":true,"showImageEffects":true,"showParticleSystems":true},"in2DMode":false,"pivot":{"x":-84.99851989746094,"y":7.20552921295166,"z":3.9951610565185549},"rotation":{"x":-0.028379365801811219,"y":0.7178770303726196,"z":-0.02930949069559574,"w":-0.6949832439422607},"size":65.16152954101563,"orthographic":false}